asyncpysupla/__init__.py
asyncpysupla-0.0.5.dist-info/LICENSE
asyncpysupla-0.0.5.dist-info/METADATA
asyncpysupla-0.0.5.dist-info/WHEEL
asyncpysupla-0.0.5.dist-info/top_level.txt
asyncpysupla-0.0.5.dist-info/RECORD
