Metadata-Version: 2.1
Name: asyncpysupla
Version: 0.0.5
Summary: Simple Supla's OpenAPI async wrapper
Home-page: https://github.com/mwegrzynek/asyncpysupla
Author: Michal Wegrzynek
Author-email: michal.wegrzynek@malloc.com.pl
License: Apache License
Platform: UNKNOWN
Classifier: Development Status :: 3 - Alpha
Classifier: License :: OSI Approved :: Apache Software License
Classifier: Topic :: Software Development :: Libraries
Classifier: Topic :: Home Automation
